odoo/addons/stock_partner_delivery_window/README.rst
odoo/addons/stock_partner_delivery_window/__init__.py
odoo/addons/stock_partner_delivery_window/__manifest__.py
odoo/addons/stock_partner_delivery_window/demo/delivery_time_window.xml
odoo/addons/stock_partner_delivery_window/i18n/es.po
odoo/addons/stock_partner_delivery_window/i18n/it.po
odoo/addons/stock_partner_delivery_window/i18n/pt_BR.po
odoo/addons/stock_partner_delivery_window/i18n/stock_partner_delivery_window.pot
odoo/addons/stock_partner_delivery_window/models/__init__.py
odoo/addons/stock_partner_delivery_window/models/delivery_time_window.py
odoo/addons/stock_partner_delivery_window/models/res_partner.py
odoo/addons/stock_partner_delivery_window/models/stock_picking.py
odoo/addons/stock_partner_delivery_window/readme/CONFIGURE.md
odoo/addons/stock_partner_delivery_window/readme/CONTRIBUTORS.md
odoo/addons/stock_partner_delivery_window/readme/CREDITS.md
odoo/addons/stock_partner_delivery_window/readme/DESCRIPTION.md
odoo/addons/stock_partner_delivery_window/security/ir.model.access.csv
odoo/addons/stock_partner_delivery_window/static/description/icon.png
odoo/addons/stock_partner_delivery_window/static/description/index.html
odoo/addons/stock_partner_delivery_window/tests/__init__.py
odoo/addons/stock_partner_delivery_window/tests/common.py
odoo/addons/stock_partner_delivery_window/tests/test_delivery_window.py
odoo/addons/stock_partner_delivery_window/tests/test_delivery_window_date.py
odoo/addons/stock_partner_delivery_window/tests/models/planned_delivery_date.py
odoo/addons/stock_partner_delivery_window/views/res_partner.xml
odoo/addons/stock_partner_delivery_window/views/stock_picking_view.xml
odoo_addon_stock_partner_delivery_window-18.0.1.2.1.2.dist-info/METADATA
odoo_addon_stock_partner_delivery_window-18.0.1.2.1.2.dist-info/WHEEL
odoo_addon_stock_partner_delivery_window-18.0.1.2.1.2.dist-info/top_level.txt
odoo_addon_stock_partner_delivery_window-18.0.1.2.1.2.dist-info/RECORD
