Metadata-Version: 2.1
Name: odoo-addon-stock_partner_delivery_window
Version: 18.0.1.2.1.2
Requires-Python: >=3.10
Requires-Dist: odoo-addon-base_time_window==18.0.*
Requires-Dist: odoo-addon-partner_tz==18.0.*
Requires-Dist: odoo==18.0.*
Summary: Define preferred delivery time windows for partners
Home-page: https://github.com/OCA/stock-logistics-workflow
License: AGPL-3
Author: Camptocamp, ACSONE SA/NV, BCIM, Odoo Community Association (OCA)
Author-email: support@odoo-community.org
Classifier: Programming Language :: Python
Classifier: Framework :: Odoo
Classifier: Framework :: Odoo :: 18.0
Classifier: License :: OSI Approved :: GNU Affero General Public License v3
